Metadata-Version: 1.1
Name: mindstrong
Version: 1.0
Summary: Mindstrong Digital Biomarker Model Fitting
Home-page: http://mindstronghealth.com
Author: Mindstrong Health Data Science
Author-email: datascience@mindstronghealth.com
License: UNKNOWN
Keywords: digital biomarkers,supervised kernel PCA,machine learning,cross-validation
Platform: UNKNOWN
Classifier: Development Status :: 5 - Production/Stable
Classifier: Intended Audience :: Developers
Classifier: License :: OSI Approved :: GNU Affero General Public License v3
Classifier: Programming Language :: Python :: 3
